[
  { "DATE": "2019-01" , "DATA TYPE": "type01"          , "STORE NUMBER": "102"    , "STORE NAME": "STORE NAME001", "CITY": "VANCOUVER"           , "POSTAL CODE": "AAAAA" , "UNIT SALES": "1"  , "SKU": "3275"   , "BRAND NAME": "BRAND NAME001" , "LTR/BTL": "0.72" },
  { "DATE": "2019-01" , "DATA TYPE": "type01"          , "STORE NUMBER": "160"    , "STORE NAME": "STORE NAME002", "CITY": "VANCOUVER"           , "POSTAL CODE": "AAAAA" , "UNIT SALES": "3"  , "SKU": "3275"   , "BRAND NAME": "BRAND NAME002" , "LTR/BTL": "0.72" },
  { "DATE": "2019-01" , "DATA TYPE": "type01"          , "STORE NUMBER": "300"    , "STORE NAME": "STORE NAME003", "CITY": "VANCOUVER"           , "POSTAL CODE": "AAAAA" , "UNIT SALES": "9"  , "SKU": "3275"   , "BRAND NAME": "BRAND NAME003" , "LTR/BTL": "0.72" },
  { "DATE": "2019-02" , "DATA TYPE": "type01"          , "STORE NUMBER": "100"    , "STORE NAME": "STORE NAME004", "CITY": "VANCOUVER"           , "POSTAL CODE": "AAAAA" , "UNIT SALES": "12" , "SKU": "56005"  , "BRAND NAME": "BRAND NAME004" , "LTR/BTL": "1.8"  },
  { "DATE": "2019-02" , "DATA TYPE": "type01"          , "STORE NUMBER": "78"     , "STORE NAME": "STORE NAME005", "CITY": "CASTLEGAR"           , "POSTAL CODE": "AAAAA" , "UNIT SALES": "1"  , "SKU": "56019"  , "BRAND NAME": "BRAND NAME005" , "LTR/BTL": "0.3"  },
  { "DATE": "2019-02" , "DATA TYPE": "type01"          , "STORE NUMBER": "94"     , "STORE NAME": "STORE NAME006", "CITY": "VANCOUVER"           , "POSTAL CODE": "AAAAA" , "UNIT SALES": "4"  , "SKU": "62091"  , "BRAND NAME": "BRAND NAME006" , "LTR/BTL": "0.3"  },
  { "DATE": "2019-02" , "DATA TYPE": "type01"          , "STORE NUMBER": "120"    , "STORE NAME": "STORE NAME007", "CITY": "RICHMOND"            , "POSTAL CODE": "AAAAA" , "UNIT SALES": "6"  , "SKU": "77289"  , "BRAND NAME": "BRAND NAME007" , "LTR/BTL": "1.8"  },
  { "DATE": "2019-02" , "DATA TYPE": "type01"          , "STORE NUMBER": "160"    , "STORE NAME": "STORE NAME008", "CITY": "VANCOUVER"           , "POSTAL CODE": "AAAAA" , "UNIT SALES": "6"  , "SKU": "77289"  , "BRAND NAME": "BRAND NAME008" , "LTR/BTL": "1.8"  },
  { "DATE": "2019-02" , "DATA TYPE": "type01"          , "STORE NUMBER": "160"    , "STORE NAME": "STORE NAME009", "CITY": "VANCOUVER"           , "POSTAL CODE": "AAAAA" , "UNIT SALES": "27" , "SKU": "131701" , "BRAND NAME": "BRAND NAME009" , "LTR/BTL": "0.75" },
  { "DATE": "2019-02" , "DATA TYPE": "type01"          , "STORE NUMBER": "100"    , "STORE NAME": "STORE NAME010", "CITY": "VANCOUVER"           , "POSTAL CODE": "AAAAA" , "UNIT SALES": "6"  , "SKU": "178660" , "BRAND NAME": "BRAND NAME010" , "LTR/BTL": "0.5"  },
  { "DATE": "2019-02" , "DATA TYPE": "type01"          , "STORE NUMBER": "100"    , "STORE NAME": "STORE NAME011", "CITY": "VANCOUVER"           , "POSTAL CODE": "AAAAA" , "UNIT SALES": "42" , "SKU": "178820" , "BRAND NAME": "BRAND NAME011" , "LTR/BTL": "0.75" },
  { "DATE": "2019-02" , "DATA TYPE": "type01"          , "STORE NUMBER": "129"    , "STORE NAME": "STORE NAME012", "CITY": "VANCOUVER"           , "POSTAL CODE": "AAAAA" , "UNIT SALES": "2"  , "SKU": "188862" , "BRAND NAME": "BRAND NAME012" , "LTR/BTL": "0.72" },
  { "DATE": "2017-01" , "DATA TYPE": "type01"          , "STORE NUMBER": "160"    , "STORE NAME": "STORE NAME013", "CITY": "VANCOUVER"           , "POSTAL CODE": "AAAAA" , "UNIT SALES": "21" , "SKU": "9035"   , "BRAND NAME": "BRAND NAME013" , "LTR/BTL": "0.7"  },
  { "DATE": "2017-01" , "DATA TYPE": "type01"          , "STORE NUMBER": "160"    , "STORE NAME": "STORE NAME014", "CITY": "VANCOUVER"           , "POSTAL CODE": "AAAAA" , "UNIT SALES": "6"  , "SKU": "188862" , "BRAND NAME": "BRAND NAME014" , "LTR/BTL": "0.72" },
  { "DATE": "2017-01" , "DATA TYPE": "type01"          , "STORE NUMBER": "76"     , "STORE NAME": "STORE NAME015", "CITY": "RICHMOND"            , "POSTAL CODE": "AAAAA" , "UNIT SALES": "18" , "SKU": "208561" , "BRAND NAME": "BRAND NAME015" , "LTR/BTL": "0.72" },
  { "DATE": "2017-01" , "DATA TYPE": "type01"          , "STORE NUMBER": "100"    , "STORE NAME": "STORE NAME016", "CITY": "VANCOUVER"           , "POSTAL CODE": "AAAAA" , "UNIT SALES": "12" , "SKU": "653931" , "BRAND NAME": "BRAND NAME016" , "LTR/BTL": "0.3"  },
  { "DATE": "2017-01" , "DATA TYPE": "type01"          , "STORE NUMBER": "76"     , "STORE NAME": "STORE NAME017", "CITY": "RICHMOND"            , "POSTAL CODE": "AAAAA" , "UNIT SALES": "6"  , "SKU": "671149" , "BRAND NAME": "BRAND NAME017" , "LTR/BTL": "1.8"  },
  { "DATE": "2017-01" , "DATA TYPE": "type01"          , "STORE NUMBER": "160"    , "STORE NAME": "STORE NAME018", "CITY": "VANCOUVER"           , "POSTAL CODE": "AAAAA" , "UNIT SALES": "6"  , "SKU": "671149" , "BRAND NAME": "BRAND NAME018" , "LTR/BTL": "1.8"  },
  { "DATE": "2017-01" , "DATA TYPE": "type01"          , "STORE NUMBER": "76"     , "STORE NAME": "STORE NAME019", "CITY": "RICHMOND"            , "POSTAL CODE": "AAAAA" , "UNIT SALES": "26" , "SKU": "895276" , "BRAND NAME": "BRAND NAME019" , "LTR/BTL": "0.3"  },
  { "DATE": "2017-02" , "DATA TYPE": "type01"          , "STORE NUMBER": "100"    , "STORE NAME": "STORE NAME020", "CITY": "VANCOUVER"           , "POSTAL CODE": "AAAAA" , "UNIT SALES": "12" , "SKU": "3208"   , "BRAND NAME": "BRAND NAME020" , "LTR/BTL": "0.72" },
  { "DATE": "2017-02" , "DATA TYPE": "type01"          , "STORE NUMBER": "160"    , "STORE NAME": "STORE NAME021", "CITY": "VANCOUVER"           , "POSTAL CODE": "AAAAA" , "UNIT SALES": "2"  , "SKU": "3275"   , "BRAND NAME": "BRAND NAME021" , "LTR/BTL": "0.72" },
  { "DATE": "2017-02" , "DATA TYPE": "type01"          , "STORE NUMBER": "76"     , "STORE NAME": "STORE NAME022", "CITY": "RICHMOND"            , "POSTAL CODE": "AAAAA" , "UNIT SALES": "67" , "SKU": "9035"   , "BRAND NAME": "BRAND NAME022" , "LTR/BTL": "0.7"  },
  { "DATE": "2017-02" , "DATA TYPE": "type01"          , "STORE NUMBER": "136"    , "STORE NAME": "STORE NAME023", "CITY": "VANCOUVER"           , "POSTAL CODE": "AAAAA" , "UNIT SALES": "1"  , "SKU": "9035"   , "BRAND NAME": "BRAND NAME023" , "LTR/BTL": "0.7"  },
  { "DATE": "2017-02" , "DATA TYPE": "type01"          , "STORE NUMBER": "160"    , "STORE NAME": "STORE NAME024", "CITY": "VANCOUVER"           , "POSTAL CODE": "AAAAA" , "UNIT SALES": "64" , "SKU": "9035"   , "BRAND NAME": "BRAND NAME024" , "LTR/BTL": "0.7"  },
  { "DATE": "2017-02" , "DATA TYPE": "type01"          , "STORE NUMBER": "160"    , "STORE NAME": "STORE NAME025", "CITY": "VANCOUVER"           , "POSTAL CODE": "AAAAA" , "UNIT SALES": "8"  , "SKU": "188862" , "BRAND NAME": "BRAND NAME025" , "LTR/BTL": "0.72" },
  { "DATE": "2017-02" , "DATA TYPE": "type01"          , "STORE NUMBER": "76"     , "STORE NAME": "STORE NAME026", "CITY": "RICHMOND"            , "POSTAL CODE": "AAAAA" , "UNIT SALES": "6"  , "SKU": "208546" , "BRAND NAME": "BRAND NAME026" , "LTR/BTL": "0.72" },
  { "DATE": "2017-02" , "DATA TYPE": "type01"          , "STORE NUMBER": "76"     , "STORE NAME": "STORE NAME027", "CITY": "RICHMOND"            , "POSTAL CODE": "AAAAA" , "UNIT SALES": "6"  , "SKU": "208561" , "BRAND NAME": "BRAND NAME027" , "LTR/BTL": "0.72" },
  { "DATE": "2017-02" , "DATA TYPE": "type01"          , "STORE NUMBER": "100"    , "STORE NAME": "STORE NAME028", "CITY": "VANCOUVER"           , "POSTAL CODE": "AAAAA" , "UNIT SALES": "12" , "SKU": "609776" , "BRAND NAME": "BRAND NAME028" , "LTR/BTL": "0.72" },
  { "DATE": "2017-02" , "DATA TYPE": "type01"          , "STORE NUMBER": "160"    , "STORE NAME": "STORE NAME029", "CITY": "VANCOUVER"           , "POSTAL CODE": "AAAAA" , "UNIT SALES": "4"  , "SKU": "609776" , "BRAND NAME": "BRAND NAME029" , "LTR/BTL": "0.72" },
  { "DATE": "2017-02" , "DATA TYPE": "type01"          , "STORE NUMBER": "76"     , "STORE NAME": "STORE NAME030", "CITY": "RICHMOND"            , "POSTAL CODE": "AAAAA" , "UNIT SALES": "30" , "SKU": "671149" , "BRAND NAME": "BRAND NAME030" , "LTR/BTL": "1.8"  },
  { "DATE": "2017-02" , "DATA TYPE": "type01"          , "STORE NUMBER": "160"    , "STORE NAME": "STORE NAME031", "CITY": "VANCOUVER"           , "POSTAL CODE": "AAAAA" , "UNIT SALES": "30" , "SKU": "671149" , "BRAND NAME": "BRAND NAME031" , "LTR/BTL": "1.8"  },
  { "DATE": "2017-02" , "DATA TYPE": "type01"          , "STORE NUMBER": "160"    , "STORE NAME": "STORE NAME032", "CITY": "VANCOUVER"           , "POSTAL CODE": "AAAAA" , "UNIT SALES": "1"  , "SKU": "778795" , "BRAND NAME": "BRAND NAME032" , "LTR/BTL": "0.72" },
  { "DATE": "2017-02" , "DATA TYPE": "type01"          , "STORE NUMBER": "76"     , "STORE NAME": "STORE NAME033", "CITY": "RICHMOND"            , "POSTAL CODE": "AAAAA" , "UNIT SALES": "37" , "SKU": "895276" , "BRAND NAME": "BRAND NAME033" , "LTR/BTL": "0.3"  },
  { "DATE": "2017-02" , "DATA TYPE": "type01"          , "STORE NUMBER": "160"    , "STORE NAME": "STORE NAME034", "CITY": "VANCOUVER"           , "POSTAL CODE": "AAAAA" , "UNIT SALES": "12" , "SKU": "895276" , "BRAND NAME": "BRAND NAME034" , "LTR/BTL": "0.3"  },
  { "DATE": "2017-03" , "DATA TYPE": "type01"          , "STORE NUMBER": "76"     , "STORE NAME": "STORE NAME035", "CITY": "RICHMOND"            , "POSTAL CODE": "AAAAA" , "UNIT SALES": "12" , "SKU": "3213"   , "BRAND NAME": "BRAND NAME035" , "LTR/BTL": "1.8"  },
  { "DATE": "2017-03" , "DATA TYPE": "type01"          , "STORE NUMBER": "160"    , "STORE NAME": "STORE NAME036", "CITY": "VANCOUVER"           , "POSTAL CODE": "AAAAA" , "UNIT SALES": "17" , "SKU": "3275"   , "BRAND NAME": "BRAND NAME036" , "LTR/BTL": "0.72" },
  { "DATE": "2017-03" , "DATA TYPE": "type01"          , "STORE NUMBER": "76"     , "STORE NAME": "STORE NAME037", "CITY": "RICHMOND"            , "POSTAL CODE": "AAAAA" , "UNIT SALES": "38" , "SKU": "9035"   , "BRAND NAME": "BRAND NAME037" , "LTR/BTL": "0.7"  },
  { "DATE": "2017-03" , "DATA TYPE": "type01"          , "STORE NUMBER": "136"    , "STORE NAME": "STORE NAME038", "CITY": "VANCOUVER"           , "POSTAL CODE": "AAAAA" , "UNIT SALES": "1"  , "SKU": "9035"   , "BRAND NAME": "BRAND NAME038" , "LTR/BTL": "0.7"  },
  { "DATE": "2017-03" , "DATA TYPE": "type01"          , "STORE NUMBER": "160"    , "STORE NAME": "STORE NAME039", "CITY": "VANCOUVER"           , "POSTAL CODE": "AAAAA" , "UNIT SALES": "28" , "SKU": "9035"   , "BRAND NAME": "BRAND NAME039" , "LTR/BTL": "0.7"  },
  { "DATE": "2017-03" , "DATA TYPE": "type01"          , "STORE NUMBER": "100"    , "STORE NAME": "STORE NAME040", "CITY": "VANCOUVER"           , "POSTAL CODE": "AAAAA" , "UNIT SALES": "6"  , "SKU": "188862" , "BRAND NAME": "BRAND NAME040" , "LTR/BTL": "0.72" },
  { "DATE": "2017-03" , "DATA TYPE": "type01"          , "STORE NUMBER": "160"    , "STORE NAME": "STORE NAME041", "CITY": "VANCOUVER"           , "POSTAL CODE": "AAAAA" , "UNIT SALES": "3"  , "SKU": "188862" , "BRAND NAME": "BRAND NAME041" , "LTR/BTL": "0.72" },
  { "DATE": "2017-03" , "DATA TYPE": "type01"          , "STORE NUMBER": "160"    , "STORE NAME": "STORE NAME042", "CITY": "VANCOUVER"           , "POSTAL CODE": "AAAAA" , "UNIT SALES": "9"  , "SKU": "547331" , "BRAND NAME": "BRAND NAME042" , "LTR/BTL": "1.8"  },
  { "DATE": "2017-03" , "DATA TYPE": "type01"          , "STORE NUMBER": "76"     , "STORE NAME": "STORE NAME043", "CITY": "RICHMOND"            , "POSTAL CODE": "AAAAA" , "UNIT SALES": "6"  , "SKU": "560227" , "BRAND NAME": "BRAND NAME043" , "LTR/BTL": "0.72" },
  { "DATE": "2017-03" , "DATA TYPE": "type01"          , "STORE NUMBER": "160"    , "STORE NAME": "STORE NAME044", "CITY": "VANCOUVER"           , "POSTAL CODE": "AAAAA" , "UNIT SALES": "8"  , "SKU": "609776" , "BRAND NAME": "BRAND NAME044" , "LTR/BTL": "0.72" },
  { "DATE": "2017-03" , "DATA TYPE": "type01"          , "STORE NUMBER": "160"    , "STORE NAME": "STORE NAME045", "CITY": "VANCOUVER"           , "POSTAL CODE": "AAAAA" , "UNIT SALES": "11" , "SKU": "669648" , "BRAND NAME": "BRAND NAME045" , "LTR/BTL": "1.8"  },
  { "DATE": "2017-03" , "DATA TYPE": "type01"          , "STORE NUMBER": "160"    , "STORE NAME": "STORE NAME046", "CITY": "VANCOUVER"           , "POSTAL CODE": "AAAAA" , "UNIT SALES": "13" , "SKU": "778795" , "BRAND NAME": "BRAND NAME046" , "LTR/BTL": "0.72" },
  { "DATE": "2017-04" , "DATA TYPE": "type01"          , "STORE NUMBER": "100"    , "STORE NAME": "STORE NAME047", "CITY": "VANCOUVER"           , "POSTAL CODE": "AAAAA" , "UNIT SALES": "12" , "SKU": "3275"   , "BRAND NAME": "BRAND NAME047" , "LTR/BTL": "0.72" },
  { "DATE": "2017-04" , "DATA TYPE": "type01"          , "STORE NUMBER": "160"    , "STORE NAME": "STORE NAME048", "CITY": "VANCOUVER"           , "POSTAL CODE": "AAAAA" , "UNIT SALES": "32" , "SKU": "3275"   , "BRAND NAME": "BRAND NAME048" , "LTR/BTL": "0.72" },
  { "DATE": "2017-04" , "DATA TYPE": "type01"          , "STORE NUMBER": "76"     , "STORE NAME": "STORE NAME049", "CITY": "RICHMOND"            , "POSTAL CODE": "AAAAA" , "UNIT SALES": "64" , "SKU": "9035"   , "BRAND NAME": "BRAND NAME049" , "LTR/BTL": "0.7"  },
  { "DATE": "2017-04" , "DATA TYPE": "type01"          , "STORE NUMBER": "136"    , "STORE NAME": "STORE NAME050", "CITY": "VANCOUVER"           , "POSTAL CODE": "AAAAA" , "UNIT SALES": "1"  , "SKU": "9035"   , "BRAND NAME": "BRAND NAME050" , "LTR/BTL": "0.7"  },
  { "DATE": "2017-04" , "DATA TYPE": "type01"          , "STORE NUMBER": "160"    , "STORE NAME": "STORE NAME051", "CITY": "VANCOUVER"           , "POSTAL CODE": "AAAAA" , "UNIT SALES": "43" , "SKU": "9035"   , "BRAND NAME": "BRAND NAME051" , "LTR/BTL": "0.7"  },
  { "DATE": "2017-04" , "DATA TYPE": "type01"          , "STORE NUMBER": "160"    , "STORE NAME": "STORE NAME052", "CITY": "VANCOUVER"           , "POSTAL CODE": "AAAAA" , "UNIT SALES": "9"  , "SKU": "188862" , "BRAND NAME": "BRAND NAME052" , "LTR/BTL": "0.72" },
  { "DATE": "2017-04" , "DATA TYPE": "type01"          , "STORE NUMBER": "76"     , "STORE NAME": "STORE NAME053", "CITY": "RICHMOND"            , "POSTAL CODE": "AAAAA" , "UNIT SALES": "1"  , "SKU": "208546" , "BRAND NAME": "BRAND NAME053" , "LTR/BTL": "0.72" },
  { "DATE": "2017-04" , "DATA TYPE": "type01"          , "STORE NUMBER": "160"    , "STORE NAME": "STORE NAME054", "CITY": "VANCOUVER"           , "POSTAL CODE": "AAAAA" , "UNIT SALES": "9"  , "SKU": "547331" , "BRAND NAME": "BRAND NAME054" , "LTR/BTL": "1.8"  },
  { "DATE": "2017-04" , "DATA TYPE": "type01"          , "STORE NUMBER": "160"    , "STORE NAME": "STORE NAME055", "CITY": "VANCOUVER"           , "POSTAL CODE": "AAAAA" , "UNIT SALES": "15" , "SKU": "609776" , "BRAND NAME": "BRAND NAME055" , "LTR/BTL": "0.72" },
  { "DATE": "2017-04" , "DATA TYPE": "type01"          , "STORE NUMBER": "160"    , "STORE NAME": "STORE NAME056", "CITY": "VANCOUVER"           , "POSTAL CODE": "AAAAA" , "UNIT SALES": "1"  , "SKU": "669648" , "BRAND NAME": "BRAND NAME056" , "LTR/BTL": "1.8"  },
  { "DATE": "2017-04" , "DATA TYPE": "type01"          , "STORE NUMBER": "76"     , "STORE NAME": "STORE NAME057", "CITY": "RICHMOND"            , "POSTAL CODE": "AAAAA" , "UNIT SALES": "24" , "SKU": "671149" , "BRAND NAME": "BRAND NAME057" , "LTR/BTL": "1.8"  },
  { "DATE": "2017-04" , "DATA TYPE": "type01"          , "STORE NUMBER": "160"    , "STORE NAME": "STORE NAME058", "CITY": "VANCOUVER"           , "POSTAL CODE": "AAAAA" , "UNIT SALES": "11" , "SKU": "778795" , "BRAND NAME": "BRAND NAME058" , "LTR/BTL": "0.72" },
  { "DATE": "2017-04" , "DATA TYPE": "type01"          , "STORE NUMBER": "76"     , "STORE NAME": "STORE NAME059", "CITY": "RICHMOND"            , "POSTAL CODE": "AAAAA" , "UNIT SALES": "35" , "SKU": "895276" , "BRAND NAME": "BRAND NAME059" , "LTR/BTL": "0.3"  },
  { "DATE": "2018-12" , "DATA TYPE": "type01"          , "STORE NUMBER": "76"     , "STORE NAME": "STORE NAME060", "CITY": "RICHMOND"            , "POSTAL CODE": "AAAAA" , "UNIT SALES": "6"  , "SKU": "3213"   , "BRAND NAME": "BRAND NAME060" , "LTR/BTL": "1.8"  },
  { "DATE": "2018-12" , "DATA TYPE": "type01"          , "STORE NUMBER": "300"    , "STORE NAME": "STORE NAME061", "CITY": "VANCOUVER"           , "POSTAL CODE": "AAAAA" , "UNIT SALES": "3"  , "SKU": "3275"   , "BRAND NAME": "BRAND NAME061" , "LTR/BTL": "0.72" },
  { "DATE": "2018-12" , "DATA TYPE": "type01"          , "STORE NUMBER": "120"    , "STORE NAME": "STORE NAME062", "CITY": "RICHMOND"            , "POSTAL CODE": "AAAAA" , "UNIT SALES": "13" , "SKU": "9035"   , "BRAND NAME": "BRAND NAME062" , "LTR/BTL": "0.7"  },
  { "DATE": "2018-12" , "DATA TYPE": "type01"          , "STORE NUMBER": "160"    , "STORE NAME": "STORE NAME063", "CITY": "VANCOUVER"           , "POSTAL CODE": "AAAAA" , "UNIT SALES": "93" , "SKU": "9035"   , "BRAND NAME": "BRAND NAME063" , "LTR/BTL": "0.7"  },
  { "DATE": "2018-12" , "DATA TYPE": "type01"          , "STORE NUMBER": "217"    , "STORE NAME": "STORE NAME064", "CITY": "BURNABY"             , "POSTAL CODE": "AAAAA" , "UNIT SALES": "18" , "SKU": "55376"  , "BRAND NAME": "BRAND NAME064" , "LTR/BTL": "0.72" },
  { "DATE": "2018-12" , "DATA TYPE": "type01"          , "STORE NUMBER": "125"    , "STORE NAME": "STORE NAME065", "CITY": "LANGFORD"            , "POSTAL CODE": "AAAAA" , "UNIT SALES": "11" , "SKU": "55376"  , "BRAND NAME": "BRAND NAME065" , "LTR/BTL": "0.72" },
  { "DATE": "2018-12" , "DATA TYPE": "type01"          , "STORE NUMBER": "76"     , "STORE NAME": "STORE NAME066", "CITY": "RICHMOND"            , "POSTAL CODE": "AAAAA" , "UNIT SALES": "14" , "SKU": "55376"  , "BRAND NAME": "BRAND NAME066" , "LTR/BTL": "0.72" },
  { "DATE": "2018-12" , "DATA TYPE": "type01"          , "STORE NUMBER": "120"    , "STORE NAME": "STORE NAME067", "CITY": "RICHMOND"            , "POSTAL CODE": "AAAAA" , "UNIT SALES": "5"  , "SKU": "55376"  , "BRAND NAME": "BRAND NAME067" , "LTR/BTL": "0.72" },
  { "DATE": "2018-12" , "DATA TYPE": "type01"          , "STORE NUMBER": "182"    , "STORE NAME": "STORE NAME068", "CITY": "SURREY"              , "POSTAL CODE": "AAAAA" , "UNIT SALES": "6"  , "SKU": "55376"  , "BRAND NAME": "BRAND NAME068" , "LTR/BTL": "0.72" },
  { "DATE": "2018-12" , "DATA TYPE": "type01"          , "STORE NUMBER": "129"    , "STORE NAME": "STORE NAME069", "CITY": "VANCOUVER"           , "POSTAL CODE": "AAAAA" , "UNIT SALES": "10" , "SKU": "55376"  , "BRAND NAME": "BRAND NAME069" , "LTR/BTL": "0.72" },
  { "DATE": "2018-12" , "DATA TYPE": "type01"          , "STORE NUMBER": "160"    , "STORE NAME": "STORE NAME070", "CITY": "VANCOUVER"           , "POSTAL CODE": "AAAAA" , "UNIT SALES": "20" , "SKU": "55376"  , "BRAND NAME": "BRAND NAME070" , "LTR/BTL": "0.72" },
  { "DATE": "2018-12" , "DATA TYPE": "type01"          , "STORE NUMBER": "120"    , "STORE NAME": "STORE NAME071", "CITY": "RICHMOND"            , "POSTAL CODE": "AAAAA" , "UNIT SALES": "1"  , "SKU": "77289"  , "BRAND NAME": "BRAND NAME071" , "LTR/BTL": "1.8"  },
  { "DATE": "2018-12" , "DATA TYPE": "type01"          , "STORE NUMBER": "233"    , "STORE NAME": "STORE NAME072", "CITY": "VANCOUVER"           , "POSTAL CODE": "AAAAA" , "UNIT SALES": "6"  , "SKU": "188912" , "BRAND NAME": "BRAND NAME072" , "LTR/BTL": "0.72" },
  { "DATE": "2018-12" , "DATA TYPE": "type01"          , "STORE NUMBER": "120"    , "STORE NAME": "STORE NAME073", "CITY": "RICHMOND"            , "POSTAL CODE": "AAAAA" , "UNIT SALES": "6"  , "SKU": "188946" , "BRAND NAME": "BRAND NAME073" , "LTR/BTL": "0.72" },
  { "DATE": "2018-12" , "DATA TYPE": "type01"          , "STORE NUMBER": "182"    , "STORE NAME": "STORE NAME074", "CITY": "SURREY"              , "POSTAL CODE": "AAAAA" , "UNIT SALES": "1"  , "SKU": "208546" , "BRAND NAME": "BRAND NAME074" , "LTR/BTL": "0.72" },
  { "DATE": "2018-12" , "DATA TYPE": "type01"          , "STORE NUMBER": "100"    , "STORE NAME": "STORE NAME075", "CITY": "VANCOUVER"           , "POSTAL CODE": "AAAAA" , "UNIT SALES": "6"  , "SKU": "217714" , "BRAND NAME": "BRAND NAME075" , "LTR/BTL": "1.8"  },
  { "DATE": "2018-12" , "DATA TYPE": "type01"          , "STORE NUMBER": "100"    , "STORE NAME": "STORE NAME076", "CITY": "VANCOUVER"           , "POSTAL CODE": "AAAAA" , "UNIT SALES": "6"  , "SKU": "217720" , "BRAND NAME": "BRAND NAME076" , "LTR/BTL": "1.8"  },
  { "DATE": "2018-12" , "DATA TYPE": "type01"          , "STORE NUMBER": "100"    , "STORE NAME": "STORE NAME077", "CITY": "VANCOUVER"           , "POSTAL CODE": "AAAAA" , "UNIT SALES": "6"  , "SKU": "217723" , "BRAND NAME": "BRAND NAME077" , "LTR/BTL": "0.72" },
  { "DATE": "2018-12" , "DATA TYPE": "type01"          , "STORE NUMBER": "160"    , "STORE NAME": "STORE NAME078", "CITY": "VANCOUVER"           , "POSTAL CODE": "AAAAA" , "UNIT SALES": "6"  , "SKU": "547331" , "BRAND NAME": "BRAND NAME078" , "LTR/BTL": "1.8"  },
  { "DATE": "2018-12" , "DATA TYPE": "type01"          , "STORE NUMBER": "120"    , "STORE NAME": "STORE NAME079", "CITY": "RICHMOND"            , "POSTAL CODE": "AAAAA" , "UNIT SALES": "3"  , "SKU": "560227" , "BRAND NAME": "BRAND NAME079" , "LTR/BTL": "0.72" },
  { "DATE": "2018-12" , "DATA TYPE": "type01"          , "STORE NUMBER": "160"    , "STORE NAME": "STORE NAME080", "CITY": "VANCOUVER"           , "POSTAL CODE": "AAAAA" , "UNIT SALES": "11" , "SKU": "609776" , "BRAND NAME": "BRAND NAME080" , "LTR/BTL": "0.72" },
  { "DATE": "2018-12" , "DATA TYPE": "type01"          , "STORE NUMBER": "218"    , "STORE NAME": "STORE NAME081", "CITY": "VICTORIA"            , "POSTAL CODE": "AAAAA" , "UNIT SALES": "10" , "SKU": "650168" , "BRAND NAME": "BRAND NAME081" , "LTR/BTL": "0.25" },
  { "DATE": "2018-12" , "DATA TYPE": "type01"          , "STORE NUMBER": "125"    , "STORE NAME": "STORE NAME082", "CITY": "LANGFORD"            , "POSTAL CODE": "AAAAA" , "UNIT SALES": "3"  , "SKU": "846261" , "BRAND NAME": "BRAND NAME082" , "LTR/BTL": "0.72" },
  { "DATE": "2018-12" , "DATA TYPE": "type01"          , "STORE NUMBER": "76"     , "STORE NAME": "STORE NAME083", "CITY": "RICHMOND"            , "POSTAL CODE": "AAAAA" , "UNIT SALES": "31" , "SKU": "895276" , "BRAND NAME": "BRAND NAME083" , "LTR/BTL": "0.3"  },
  { "DATE": "2018-11" , "DATA TYPE": "type01"          , "STORE NUMBER": "300"    , "STORE NAME": "STORE NAME084", "CITY": "VANCOUVER"           , "POSTAL CODE": "AAAAA" , "UNIT SALES": "7"  , "SKU": "3275"   , "BRAND NAME": "BRAND NAME084" , "LTR/BTL": "0.72" },
  { "DATE": "2018-11" , "DATA TYPE": "type01"          , "STORE NUMBER": "120"    , "STORE NAME": "STORE NAME085", "CITY": "RICHMOND"            , "POSTAL CODE": "AAAAA" , "UNIT SALES": "13" , "SKU": "9035"   , "BRAND NAME": "BRAND NAME085" , "LTR/BTL": "0.7"  },
  { "DATE": "2018-11" , "DATA TYPE": "type01"          , "STORE NUMBER": "160"    , "STORE NAME": "STORE NAME086", "CITY": "VANCOUVER"           , "POSTAL CODE": "AAAAA" , "UNIT SALES": "36" , "SKU": "9035"   , "BRAND NAME": "BRAND NAME086" , "LTR/BTL": "0.7"  },
  { "DATE": "2018-11" , "DATA TYPE": "type01"          , "STORE NUMBER": "125"    , "STORE NAME": "STORE NAME087", "CITY": "LANGFORD"            , "POSTAL CODE": "AAAAA" , "UNIT SALES": "27" , "SKU": "55376"  , "BRAND NAME": "BRAND NAME087" , "LTR/BTL": "0.72" },
  { "DATE": "2018-11" , "DATA TYPE": "type01"          , "STORE NUMBER": "102"    , "STORE NAME": "STORE NAME088", "CITY": "VANCOUVER"           , "POSTAL CODE": "AAAAA" , "UNIT SALES": "6"  , "SKU": "55376"  , "BRAND NAME": "BRAND NAME088" , "LTR/BTL": "0.72" },
  { "DATE": "2018-11" , "DATA TYPE": "type01"          , "STORE NUMBER": "160"    , "STORE NAME": "STORE NAME089", "CITY": "VANCOUVER"           , "POSTAL CODE": "AAAAA" , "UNIT SALES": "3"  , "SKU": "55376"  , "BRAND NAME": "BRAND NAME089" , "LTR/BTL": "0.72" },
  { "DATE": "2018-11" , "DATA TYPE": "type01"          , "STORE NUMBER": "120"    , "STORE NAME": "STORE NAME090", "CITY": "RICHMOND"            , "POSTAL CODE": "AAAAA" , "UNIT SALES": "1"  , "SKU": "77289"  , "BRAND NAME": "BRAND NAME090" , "LTR/BTL": "1.8"  },
  { "DATE": "2018-11" , "DATA TYPE": "type01"          , "STORE NUMBER": "100"    , "STORE NAME": "STORE NAME091", "CITY": "VANCOUVER"           , "POSTAL CODE": "AAAAA" , "UNIT SALES": "12" , "SKU": "124915" , "BRAND NAME": "BRAND NAME091" , "LTR/BTL": "0.25" },
  { "DATE": "2018-11" , "DATA TYPE": "type01"          , "STORE NUMBER": "120"    , "STORE NAME": "STORE NAME092", "CITY": "RICHMOND"            , "POSTAL CODE": "AAAAA" , "UNIT SALES": "5"  , "SKU": "188946" , "BRAND NAME": "BRAND NAME092" , "LTR/BTL": "0.72" },
  { "DATE": "2018-11" , "DATA TYPE": "type01"          , "STORE NUMBER": "244"    , "STORE NAME": "STORE NAME093", "CITY": "RICHMOND"            , "POSTAL CODE": "AAAAA" , "UNIT SALES": "6"  , "SKU": "208546" , "BRAND NAME": "BRAND NAME093" , "LTR/BTL": "0.72" },
  { "DATE": "2018-11" , "DATA TYPE": "type01"          , "STORE NUMBER": "76"     , "STORE NAME": "STORE NAME094", "CITY": "RICHMOND"            , "POSTAL CODE": "AAAAA" , "UNIT SALES": "3"  , "SKU": "466284" , "BRAND NAME": "BRAND NAME094" , "LTR/BTL": "0.5"  },
  { "DATE": "2018-11" , "DATA TYPE": "type01"          , "STORE NUMBER": "120"    , "STORE NAME": "STORE NAME095", "CITY": "RICHMOND"            , "POSTAL CODE": "AAAAA" , "UNIT SALES": "2"  , "SKU": "560227" , "BRAND NAME": "BRAND NAME095" , "LTR/BTL": "0.72" },
  { "DATE": "2018-11" , "DATA TYPE": "type01"          , "STORE NUMBER": "160"    , "STORE NAME": "STORE NAME096", "CITY": "VANCOUVER"           , "POSTAL CODE": "AAAAA" , "UNIT SALES": "8"  , "SKU": "609776" , "BRAND NAME": "BRAND NAME096" , "LTR/BTL": "0.72" },
  { "DATE": "2018-11" , "DATA TYPE": "type01"          , "STORE NUMBER": "218"    , "STORE NAME": "STORE NAME097", "CITY": "VICTORIA"            , "POSTAL CODE": "AAAAA" , "UNIT SALES": "5"  , "SKU": "650168" , "BRAND NAME": "BRAND NAME097" , "LTR/BTL": "0.25" },
  { "DATE": "2018-11" , "DATA TYPE": "type01"          , "STORE NUMBER": "160"    , "STORE NAME": "STORE NAME098", "CITY": "VANCOUVER"           , "POSTAL CODE": "AAAAA" , "UNIT SALES": "1"  , "SKU": "669648" , "BRAND NAME": "BRAND NAME098" , "LTR/BTL": "1.8"  },
  { "DATE": "2017-04" , "DATA TYPE": "type02" , "STORE NUMBER": "303583" ,          "STORE NAME": "STORE NAME099", "CITY": "RICHMOND"            , "POSTAL CODE": "AAAAA"  , "UNIT SALES": "12" , "SKU": "208561" , "BRAND NAME":"BRAND NAME099"  , "LTR/BTL": "0.72" },
  { "DATE": "2017-04" , "DATA TYPE": "type02" , "STORE NUMBER": "208857" ,          "STORE NAME": "STORE NAME100", "CITY": "RICHMOND"            , "POSTAL CODE": "AAAAA"  , "UNIT SALES": "15" , "SKU": "268151" , "BRAND NAME":"BRAND NAME100"  , "LTR/BTL": "1.8"  },
  { "DATE": "2017-04" , "DATA TYPE": "type02" , "STORE NUMBER": "302449" ,          "STORE NAME": "STORE NAME101", "CITY": "RICHMOND"            , "POSTAL CODE": "AAAAA"  , "UNIT SALES": "15" , "SKU": "268151" , "BRAND NAME":"BRAND NAME101"  , "LTR/BTL": "1.8"  },
  { "DATE": "2017-04" , "DATA TYPE": "type02" , "STORE NUMBER": "302779" ,          "STORE NAME": "STORE NAME102", "CITY": "RICHMOND"            , "POSTAL CODE": "AAAAA"  , "UNIT SALES": "6"  , "SKU": "268151" , "BRAND NAME":"BRAND NAME102"  , "LTR/BTL": "1.8"  },
  { "DATE": "2017-04" , "DATA TYPE": "type02" , "STORE NUMBER": "304589" ,          "STORE NAME": "STORE NAME103", "CITY": "RICHMOND"            , "POSTAL CODE": "AAAAA"  , "UNIT SALES": "6"  , "SKU": "547331" , "BRAND NAME":"BRAND NAME103"  , "LTR/BTL": "1.8"  },
  { "DATE": "2017-04" , "DATA TYPE": "type02" , "STORE NUMBER": "142519" ,          "STORE NAME": "STORE NAME104", "CITY": "VANCOUVER"           , "POSTAL CODE": "AAAAA"  , "UNIT SALES": "6"  , "SKU": "547331" , "BRAND NAME":"BRAND NAME104"  , "LTR/BTL": "1.8"  },
  { "DATE": "2017-04" , "DATA TYPE": "type02" , "STORE NUMBER": "153824" ,          "STORE NAME": "STORE NAME105", "CITY": "RICHMOND"            , "POSTAL CODE": "AAAAA"  , "UNIT SALES": "36" , "SKU": "599589" , "BRAND NAME":"BRAND NAME105"  , "LTR/BTL": "0.3"  },
  { "DATE": "2017-04" , "DATA TYPE": "type02" , "STORE NUMBER": "208857" ,          "STORE NAME": "STORE NAME106", "CITY": "RICHMOND"            , "POSTAL CODE": "AAAAA"  , "UNIT SALES": "24" , "SKU": "599589" , "BRAND NAME":"BRAND NAME106"  , "LTR/BTL": "0.3"  },
  { "DATE": "2017-04" , "DATA TYPE": "type02" , "STORE NUMBER": "302449" ,          "STORE NAME": "STORE NAME107", "CITY": "RICHMOND"            , "POSTAL CODE": "AAAAA"  , "UNIT SALES": "24" , "SKU": "599589" , "BRAND NAME":"BRAND NAME107"  , "LTR/BTL": "0.3"  },
  { "DATE": "2017-04" , "DATA TYPE": "type02" , "STORE NUMBER": "200659" ,          "STORE NAME": "STORE NAME108", "CITY": "VANCOUVER"           , "POSTAL CODE": "AAAAA"  , "UNIT SALES": "24" , "SKU": "599589" , "BRAND NAME":"BRAND NAME108"  , "LTR/BTL": "0.3"  },
  { "DATE": "2017-04" , "DATA TYPE": "type02" , "STORE NUMBER": "142896" ,          "STORE NAME": "STORE NAME109", "CITY": "VANCOUVER"           , "POSTAL CODE": "AAAAA"  , "UNIT SALES": "12" , "SKU": "603639" , "BRAND NAME":"BRAND NAME109"  , "LTR/BTL": "0.72" },
  { "DATE": "2017-04" , "DATA TYPE": "type02" , "STORE NUMBER": "302301" ,          "STORE NAME": "STORE NAME110", "CITY": "VANCOUVER"           , "POSTAL CODE": "AAAAA"  , "UNIT SALES": "12" , "SKU": "603639" , "BRAND NAME":"BRAND NAME110"  , "LTR/BTL": "0.72" },
  { "DATE": "2017-04" , "DATA TYPE": "type02" , "STORE NUMBER": "303583" ,          "STORE NAME": "STORE NAME111", "CITY": "RICHMOND"            , "POSTAL CODE": "AAAAA"  , "UNIT SALES": "12" , "SKU": "609776" , "BRAND NAME":"BRAND NAME111"  , "LTR/BTL": "0.72" },
  { "DATE": "2017-04" , "DATA TYPE": "type02" , "STORE NUMBER": "54302"  ,          "STORE NAME": "STORE NAME112", "CITY": "VANCOUVER"           , "POSTAL CODE": "AAAAA"  , "UNIT SALES": "5"  , "SKU": "609776" , "BRAND NAME":"BRAND NAME112"  , "LTR/BTL": "0.72" },
  { "DATE": "2017-04" , "DATA TYPE": "type02" , "STORE NUMBER": "125619" ,          "STORE NAME": "STORE NAME113", "CITY": "VANCOUVER"           , "POSTAL CODE": "AAAAA"  , "UNIT SALES": "2"  , "SKU": "609776" , "BRAND NAME":"BRAND NAME113"  , "LTR/BTL": "0.72" },
  { "DATE": "2017-04" , "DATA TYPE": "type02" , "STORE NUMBER": "153824" ,          "STORE NAME": "STORE NAME114", "CITY": "RICHMOND"            , "POSTAL CODE": "AAAAA"  , "UNIT SALES": "18" , "SKU": "671149" , "BRAND NAME":"BRAND NAME114"  , "LTR/BTL": "1.8"  },
  { "DATE": "2017-04" , "DATA TYPE": "type02" , "STORE NUMBER": "208857" ,          "STORE NAME": "STORE NAME115", "CITY": "RICHMOND"            , "POSTAL CODE": "AAAAA"  , "UNIT SALES": "3"  , "SKU": "671149" , "BRAND NAME":"BRAND NAME115"  , "LTR/BTL": "1.8"  },
  { "DATE": "2017-04" , "DATA TYPE": "type02" , "STORE NUMBER": "302449" ,          "STORE NAME": "STORE NAME116", "CITY": "RICHMOND"            , "POSTAL CODE": "AAAAA"  , "UNIT SALES": "3"  , "SKU": "671149" , "BRAND NAME":"BRAND NAME116"  , "LTR/BTL": "1.8"  },
  { "DATE": "2017-04" , "DATA TYPE": "type02" , "STORE NUMBER": "303934" ,          "STORE NAME": "STORE NAME117", "CITY": "RICHMOND"            , "POSTAL CODE": "AAAAA"  , "UNIT SALES": "6"  , "SKU": "671149" , "BRAND NAME":"BRAND NAME117"  , "LTR/BTL": "1.8"  },
  { "DATE": "2017-04" , "DATA TYPE": "type02" , "STORE NUMBER": "208003" ,          "STORE NAME": "STORE NAME118", "CITY": "VANCOUVER"           , "POSTAL CODE": "AAAAA"  , "UNIT SALES": "12" , "SKU": "671149" , "BRAND NAME":"BRAND NAME118"  , "LTR/BTL": "1.8"  },
  { "DATE": "2017-04" , "DATA TYPE": "type02" , "STORE NUMBER": "54302"  ,          "STORE NAME": "STORE NAME119", "CITY": "VANCOUVER"           , "POSTAL CODE": "AAAAA"  , "UNIT SALES": "1"  , "SKU": "778795" , "BRAND NAME":"BRAND NAME119"  , "LTR/BTL": "0.72" },
  { "DATE": "2017-04" , "DATA TYPE": "type02" , "STORE NUMBER": "193145" ,          "STORE NAME": "STORE NAME120", "CITY": "RICHMOND"            , "POSTAL CODE": "AAAAA"  , "UNIT SALES": "12" , "SKU": "895276" , "BRAND NAME":"BRAND NAME120"  , "LTR/BTL": "0.3"  },
  { "DATE": "2017-03" , "DATA TYPE": "type02" , "STORE NUMBER": "212780" ,          "STORE NAME": "STORE NAME121", "CITY": "VICTORIA"            , "POSTAL CODE": "AAAAA"  , "UNIT SALES": "24" , "SKU": "3208"   , "BRAND NAME":"BRAND NAME121"  , "LTR/BTL": "0.72" },
  { "DATE": "2017-03" , "DATA TYPE": "type02" , "STORE NUMBER": "302449" ,          "STORE NAME": "STORE NAME122", "CITY": "RICHMOND"            , "POSTAL CODE": "AAAAA"  , "UNIT SALES": "6"  , "SKU": "3213"   , "BRAND NAME":"BRAND NAME122"  , "LTR/BTL": "1.8"  },
  { "DATE": "2017-03" , "DATA TYPE": "type02" , "STORE NUMBER": "212780" ,          "STORE NAME": "STORE NAME123", "CITY": "VICTORIA"            , "POSTAL CODE": "AAAAA"  , "UNIT SALES": "24" , "SKU": "3275"   , "BRAND NAME":"BRAND NAME123"  , "LTR/BTL": "0.72" },
  { "DATE": "2017-03" , "DATA TYPE": "type02" , "STORE NUMBER": "306308" ,          "STORE NAME": "STORE NAME124", "CITY": "VICTORIA"            , "POSTAL CODE": "AAAAA"  , "UNIT SALES": "12" , "SKU": "3275"   , "BRAND NAME":"BRAND NAME124"  , "LTR/BTL": "0.72" },
  { "DATE": "2017-03" , "DATA TYPE": "type02" , "STORE NUMBER": "130765" ,          "STORE NAME": "STORE NAME125", "CITY": "RICHMOND"            , "POSTAL CODE": "AAAAA"  , "UNIT SALES": "4"  , "SKU": "9035"   , "BRAND NAME":"BRAND NAME125"  , "LTR/BTL": "0.7"  },
  { "DATE": "2017-03" , "DATA TYPE": "type02" , "STORE NUMBER": "175261" ,          "STORE NAME": "STORE NAME126", "CITY": "RICHMOND"            , "POSTAL CODE": "AAAAA"  , "UNIT SALES": "1"  , "SKU": "9035"   , "BRAND NAME":"BRAND NAME126"  , "LTR/BTL": "0.7"  },
  { "DATE": "2017-03" , "DATA TYPE": "type02" , "STORE NUMBER": "305293" ,          "STORE NAME": "STORE NAME127", "CITY": "VANCOUVER"           , "POSTAL CODE": "AAAAA"  , "UNIT SALES": "1"  , "SKU": "9035"   , "BRAND NAME":"BRAND NAME127"  , "LTR/BTL": "0.7"  },
  { "DATE": "2017-03" , "DATA TYPE": "type02" , "STORE NUMBER": "212780" ,          "STORE NAME": "STORE NAME128", "CITY": "VICTORIA"            , "POSTAL CODE": "AAAAA"  , "UNIT SALES": "12" , "SKU": "62091"  , "BRAND NAME":"BRAND NAME128"  , "LTR/BTL": "0.3"  },
  { "DATE": "2017-03" , "DATA TYPE": "type02" , "STORE NUMBER": "306819" ,          "STORE NAME": "STORE NAME129", "CITY": "VANCOUVER"           , "POSTAL CODE": "AAAAA"  , "UNIT SALES": "3"  , "SKU": "188862" , "BRAND NAME":"BRAND NAME129"  , "LTR/BTL": "0.72" },
  { "DATE": "2017-03" , "DATA TYPE": "type02" , "STORE NUMBER": "215026" ,          "STORE NAME": "STORE NAME130", "CITY": "VANCOUVER"           , "POSTAL CODE": "AAAAA"  , "UNIT SALES": "6"  , "SKU": "188904" , "BRAND NAME":"BRAND NAME130"  , "LTR/BTL": "1.8"  },
  { "DATE": "2017-03" , "DATA TYPE": "type02" , "STORE NUMBER": "306243" ,          "STORE NAME": "STORE NAME131", "CITY": "RICHMOND"            , "POSTAL CODE": "AAAAA"  , "UNIT SALES": "6"  , "SKU": "208546" , "BRAND NAME":"BRAND NAME131"  , "LTR/BTL": "0.72" },
  { "DATE": "2017-03" , "DATA TYPE": "type02" , "STORE NUMBER": "152155" ,          "STORE NAME": "STORE NAME132", "CITY": "VANCOUVER"           , "POSTAL CODE": "AAAAA"  , "UNIT SALES": "6"  , "SKU": "208546" , "BRAND NAME":"BRAND NAME132"  , "LTR/BTL": "0.72" },
  { "DATE": "2017-03" , "DATA TYPE": "type02" , "STORE NUMBER": "215314" ,          "STORE NAME": "STORE NAME133", "CITY": "VANCOUVER"           , "POSTAL CODE": "AAAAA"  , "UNIT SALES": "12" , "SKU": "208546" , "BRAND NAME":"BRAND NAME133"  , "LTR/BTL": "0.72" },
  { "DATE": "2017-03" , "DATA TYPE": "type02" , "STORE NUMBER": "304550" ,          "STORE NAME": "STORE NAME134", "CITY": "VANCOUVER"           , "POSTAL CODE": "AAAAA"  , "UNIT SALES": "6"  , "SKU": "208546" , "BRAND NAME":"BRAND NAME134"  , "LTR/BTL": "0.72" },
  { "DATE": "2017-03" , "DATA TYPE": "type02" , "STORE NUMBER": "215026" ,          "STORE NAME": "STORE NAME135", "CITY": "VANCOUVER"           , "POSTAL CODE": "AAAAA"  , "UNIT SALES": "6"  , "SKU": "208561" , "BRAND NAME":"BRAND NAME135"  , "LTR/BTL": "0.72" },
  { "DATE": "2017-03" , "DATA TYPE": "type02" , "STORE NUMBER": "153824" ,          "STORE NAME": "STORE NAME136", "CITY": "RICHMOND"            , "POSTAL CODE": "AAAAA"  , "UNIT SALES": "12" , "SKU": "466284" , "BRAND NAME":"BRAND NAME136"  , "LTR/BTL": "0.5"  },
  { "DATE": "2017-03" , "DATA TYPE": "type02" , "STORE NUMBER": "304550" ,          "STORE NAME": "STORE NAME137", "CITY": "VANCOUVER"           , "POSTAL CODE": "AAAAA"  , "UNIT SALES": "12" , "SKU": "466284" , "BRAND NAME":"BRAND NAME137"  , "LTR/BTL": "0.5"  },
  { "DATE": "2017-03" , "DATA TYPE": "type02" , "STORE NUMBER": "195477" ,          "STORE NAME": "STORE NAME138", "CITY": "VANCOUVER"           , "POSTAL CODE": "AAAAA"  , "UNIT SALES": "12" , "SKU": "466284" , "BRAND NAME":"BRAND NAME138"  , "LTR/BTL": "0.5"  },
  { "DATE": "2017-03" , "DATA TYPE": "type02" , "STORE NUMBER": "307242" ,          "STORE NAME": "STORE NAME139", "CITY": "RICHMOND"            , "POSTAL CODE": "AAAAA"  , "UNIT SALES": "12" , "SKU": "599589" , "BRAND NAME":"BRAND NAME139"  , "LTR/BTL": "0.3"  },
  { "DATE": "2017-03" , "DATA TYPE": "type02" , "STORE NUMBER": "301112" ,          "STORE NAME": "STORE NAME140", "CITY": "VANCOUVER"           , "POSTAL CODE": "AAAAA"  , "UNIT SALES": "12" , "SKU": "599589" , "BRAND NAME":"BRAND NAME140"  , "LTR/BTL": "0.3"  },
  { "DATE": "2017-03" , "DATA TYPE": "type02" , "STORE NUMBER": "302486" ,          "STORE NAME": "STORE NAME141", "CITY": "REVELSTOKE"          , "POSTAL CODE": "AAAAA"  , "UNIT SALES": "12" , "SKU": "603639" , "BRAND NAME":"BRAND NAME141"  , "LTR/BTL": "0.72" },
  { "DATE": "2017-03" , "DATA TYPE": "type02" , "STORE NUMBER": "208857" ,          "STORE NAME": "STORE NAME142", "CITY": "RICHMOND"            , "POSTAL CODE": "AAAAA"  , "UNIT SALES": "12" , "SKU": "603639" , "BRAND NAME":"BRAND NAME142"  , "LTR/BTL": "0.72" },
  { "DATE": "2017-03" , "DATA TYPE": "type02" , "STORE NUMBER": "302449" ,          "STORE NAME": "STORE NAME143", "CITY": "RICHMOND"            , "POSTAL CODE": "AAAAA"  , "UNIT SALES": "12" , "SKU": "603639" , "BRAND NAME":"BRAND NAME143"  , "LTR/BTL": "0.72" },
  { "DATE": "2017-03" , "DATA TYPE": "type02" , "STORE NUMBER": "300546" ,          "STORE NAME": "STORE NAME144", "CITY": "WHISTLER"            , "POSTAL CODE": "AAAAA"  , "UNIT SALES": "24" , "SKU": "603639" , "BRAND NAME":"BRAND NAME144"  , "LTR/BTL": "0.72" },
  { "DATE": "2017-03" , "DATA TYPE": "type02" , "STORE NUMBER": "195477" ,          "STORE NAME": "STORE NAME145", "CITY": "VANCOUVER"           , "POSTAL CODE": "AAAAA"  , "UNIT SALES": "24" , "SKU": "603639" , "BRAND NAME":"BRAND NAME145"  , "LTR/BTL": "0.72" },
  { "DATE": "2017-03" , "DATA TYPE": "type02" , "STORE NUMBER": "212780" ,          "STORE NAME": "STORE NAME146", "CITY": "VICTORIA"            , "POSTAL CODE": "AAAAA"  , "UNIT SALES": "24" , "SKU": "609776" , "BRAND NAME":"BRAND NAME146"  , "LTR/BTL": "0.72" },
  { "DATE": "2017-03" , "DATA TYPE": "type02" , "STORE NUMBER": "205992" ,          "STORE NAME": "STORE NAME147", "CITY": "VANCOUVER"           , "POSTAL CODE": "AAAAA"  , "UNIT SALES": "12" , "SKU": "653931" , "BRAND NAME":"BRAND NAME147"  , "LTR/BTL": "0.3"  },
  { "DATE": "2017-03" , "DATA TYPE": "type02" , "STORE NUMBER": "195502" ,          "STORE NAME": "STORE NAME148", "CITY": "VANCOUVER"           , "POSTAL CODE": "AAAAA"  , "UNIT SALES": "24" , "SKU": "666255" , "BRAND NAME":"BRAND NAME148"  , "LTR/BTL": "0.35" },
  { "DATE": "2017-01" , "DATA TYPE": "type02" , "STORE NUMBER": "208857" ,          "STORE NAME": "STORE NAME149", "CITY": "RICHMOND"            , "POSTAL CODE": "AAAAA"  , "UNIT SALES": "18" , "SKU": "208546" , "BRAND NAME":"BRAND NAME149"  , "LTR/BTL": "0.72" },
  { "DATE": "2017-01" , "DATA TYPE": "type02" , "STORE NUMBER": "302449" ,          "STORE NAME": "STORE NAME150", "CITY": "RICHMOND"            , "POSTAL CODE": "AAAAA"  , "UNIT SALES": "18" , "SKU": "208546" , "BRAND NAME":"BRAND NAME150"  , "LTR/BTL": "0.72" },
  { "DATE": "2017-01" , "DATA TYPE": "type02" , "STORE NUMBER": "306243" ,          "STORE NAME": "STORE NAME151", "CITY": "RICHMOND"            , "POSTAL CODE": "AAAAA"  , "UNIT SALES": "12" , "SKU": "208546" , "BRAND NAME":"BRAND NAME151"  , "LTR/BTL": "0.72" },
  { "DATE": "2017-01" , "DATA TYPE": "type02" , "STORE NUMBER": "307242" ,          "STORE NAME": "STORE NAME152", "CITY": "RICHMOND"            , "POSTAL CODE": "AAAAA"  , "UNIT SALES": "6"  , "SKU": "208546" , "BRAND NAME":"BRAND NAME152"  , "LTR/BTL": "0.72" },
  { "DATE": "2017-01" , "DATA TYPE": "type02" , "STORE NUMBER": "152155" ,          "STORE NAME": "STORE NAME153", "CITY": "VANCOUVER"           , "POSTAL CODE": "AAAAA"  , "UNIT SALES": "18" , "SKU": "208546" , "BRAND NAME":"BRAND NAME153"  , "LTR/BTL": "0.72" },
  { "DATE": "2017-01" , "DATA TYPE": "type02" , "STORE NUMBER": "306819" ,          "STORE NAME": "STORE NAME154", "CITY": "VANCOUVER"           , "POSTAL CODE": "AAAAA"  , "UNIT SALES": "18" , "SKU": "208546" , "BRAND NAME":"BRAND NAME154"  , "LTR/BTL": "0.72" },
  { "DATE": "2017-01" , "DATA TYPE": "type02" , "STORE NUMBER": "306819" ,          "STORE NAME": "STORE NAME155", "CITY": "VANCOUVER"           , "POSTAL CODE": "AAAAA"  , "UNIT SALES": "12" , "SKU": "208561" , "BRAND NAME":"BRAND NAME155"  , "LTR/BTL": "0.72" },
  { "DATE": "2017-01" , "DATA TYPE": "type02" , "STORE NUMBER": "153824" ,          "STORE NAME": "STORE NAME156", "CITY": "RICHMOND"            , "POSTAL CODE": "AAAAA"  , "UNIT SALES": "12" , "SKU": "466284" , "BRAND NAME":"BRAND NAME156"  , "LTR/BTL": "0.5"  },
  { "DATE": "2017-01" , "DATA TYPE": "type02" , "STORE NUMBER": "208857" ,          "STORE NAME": "STORE NAME157", "CITY": "RICHMOND"            , "POSTAL CODE": "AAAAA"  , "UNIT SALES": "6"  , "SKU": "466284" , "BRAND NAME":"BRAND NAME157"  , "LTR/BTL": "0.5"  },
  { "DATE": "2017-01" , "DATA TYPE": "type02" , "STORE NUMBER": "302449" ,          "STORE NAME": "STORE NAME158", "CITY": "RICHMOND"            , "POSTAL CODE": "AAAAA"  , "UNIT SALES": "6"  , "SKU": "466284" , "BRAND NAME":"BRAND NAME158"  , "LTR/BTL": "0.5"  },
  { "DATE": "2017-01" , "DATA TYPE": "type02" , "STORE NUMBER": "195477" ,          "STORE NAME": "STORE NAME159", "CITY": "VANCOUVER"           , "POSTAL CODE": "AAAAA"  , "UNIT SALES": "12" , "SKU": "466284" , "BRAND NAME":"BRAND NAME159"  , "LTR/BTL": "0.5"  },
  { "DATE": "2017-01" , "DATA TYPE": "type02" , "STORE NUMBER": "153824" ,          "STORE NAME": "STORE NAME160", "CITY": "RICHMOND"            , "POSTAL CODE": "AAAAA"  , "UNIT SALES": "24" , "SKU": "599589" , "BRAND NAME":"BRAND NAME160"  , "LTR/BTL": "0.3"  },
  { "DATE": "2017-01" , "DATA TYPE": "type02" , "STORE NUMBER": "208857" ,          "STORE NAME": "STORE NAME161", "CITY": "RICHMOND"            , "POSTAL CODE": "AAAAA"  , "UNIT SALES": "24" , "SKU": "599589" , "BRAND NAME":"BRAND NAME161"  , "LTR/BTL": "0.3"  },
  { "DATE": "2017-01" , "DATA TYPE": "type02" , "STORE NUMBER": "302449" ,          "STORE NAME": "STORE NAME162", "CITY": "RICHMOND"            , "POSTAL CODE": "AAAAA"  , "UNIT SALES": "24" , "SKU": "599589" , "BRAND NAME":"BRAND NAME162"  , "LTR/BTL": "0.3"  },
  { "DATE": "2017-01" , "DATA TYPE": "type02" , "STORE NUMBER": "301112" ,          "STORE NAME": "STORE NAME163", "CITY": "VANCOUVER"           , "POSTAL CODE": "AAAAA"  , "UNIT SALES": "12" , "SKU": "599589" , "BRAND NAME":"BRAND NAME163"  , "LTR/BTL": "0.3"  },
  { "DATE": "2017-01" , "DATA TYPE": "type02" , "STORE NUMBER": "195477" ,          "STORE NAME": "STORE NAME164", "CITY": "VANCOUVER"           , "POSTAL CODE": "AAAAA"  , "UNIT SALES": "12" , "SKU": "599589" , "BRAND NAME":"BRAND NAME164"  , "LTR/BTL": "0.3"  },
  { "DATE": "2017-01" , "DATA TYPE": "type02" , "STORE NUMBER": "300546" ,          "STORE NAME": "STORE NAME165", "CITY": "WHISTLER"            , "POSTAL CODE": "AAAAA"  , "UNIT SALES": "12" , "SKU": "603639" , "BRAND NAME":"BRAND NAME165"  , "LTR/BTL": "0.72" },
  { "DATE": "2017-01" , "DATA TYPE": "type02" , "STORE NUMBER": "195477" ,          "STORE NAME": "STORE NAME166", "CITY": "VANCOUVER"           , "POSTAL CODE": "AAAAA"  , "UNIT SALES": "12" , "SKU": "603639" , "BRAND NAME":"BRAND NAME166"  , "LTR/BTL": "0.72" },
  { "DATE": "2017-01" , "DATA TYPE": "type02" , "STORE NUMBER": "193434" ,          "STORE NAME": "STORE NAME167", "CITY": "WHISTLER"            , "POSTAL CODE": "AAAAA"  , "UNIT SALES": "12" , "SKU": "603639" , "BRAND NAME":"BRAND NAME167"  , "LTR/BTL": "0.72" },
  { "DATE": "2017-01" , "DATA TYPE": "type02" , "STORE NUMBER": "153824" ,          "STORE NAME": "STORE NAME168", "CITY": "RICHMOND"            , "POSTAL CODE": "AAAAA"  , "UNIT SALES": "18" , "SKU": "671149" , "BRAND NAME":"BRAND NAME168"  , "LTR/BTL": "1.8"  },
  { "DATE": "2017-01" , "DATA TYPE": "type02" , "STORE NUMBER": "161856" ,          "STORE NAME": "STORE NAME169", "CITY": "RICHMOND"            , "POSTAL CODE": "AAAAA"  , "UNIT SALES": "24" , "SKU": "671149" , "BRAND NAME":"BRAND NAME169"  , "LTR/BTL": "1.8"  },
  { "DATE": "2017-01" , "DATA TYPE": "type02" , "STORE NUMBER": "208857" ,          "STORE NAME": "STORE NAME170", "CITY": "RICHMOND"            , "POSTAL CODE": "AAAAA"  , "UNIT SALES": "24" , "SKU": "671149" , "BRAND NAME":"BRAND NAME170"  , "LTR/BTL": "1.8"  },
  { "DATE": "2017-01" , "DATA TYPE": "type02" , "STORE NUMBER": "302449" ,          "STORE NAME": "STORE NAME171", "CITY": "RICHMOND"            , "POSTAL CODE": "AAAAA"  , "UNIT SALES": "24" , "SKU": "671149" , "BRAND NAME":"BRAND NAME171"  , "LTR/BTL": "1.8"  },
  { "DATE": "2017-01" , "DATA TYPE": "type02" , "STORE NUMBER": "306243" ,          "STORE NAME": "STORE NAME172", "CITY": "RICHMOND"            , "POSTAL CODE": "AAAAA"  , "UNIT SALES": "12" , "SKU": "671149" , "BRAND NAME":"BRAND NAME172"  , "LTR/BTL": "1.8"  },
  { "DATE": "2017-01" , "DATA TYPE": "type02" , "STORE NUMBER": "306819" ,          "STORE NAME": "STORE NAME173", "CITY": "VANCOUVER"           , "POSTAL CODE": "AAAAA"  , "UNIT SALES": "18" , "SKU": "671149" , "BRAND NAME":"BRAND NAME173"  , "LTR/BTL": "1.8"  },
  { "DATE": "2017-01" , "DATA TYPE": "type02" , "STORE NUMBER": "303583" ,          "STORE NAME": "STORE NAME174", "CITY": "RICHMOND"            , "POSTAL CODE": "AAAAA"  , "UNIT SALES": "12" , "SKU": "895276" , "BRAND NAME":"BRAND NAME174"  , "LTR/BTL": "0.3"  },
  { "DATE": "2017-01" , "DATA TYPE": "type02" , "STORE NUMBER": "306708" ,          "STORE NAME": "STORE NAME175", "CITY": "RICHMOND"            , "POSTAL CODE": "AAAAA"  , "UNIT SALES": "6"  , "SKU": "895276" , "BRAND NAME":"BRAND NAME175"  , "LTR/BTL": "0.3"  }
]
